banglanlptoolkit/__init__.py
banglanlptoolkit/banglaaugmentation.py
banglanlptoolkit/banglapunctuation.py
banglanlptoolkit/banglatextmentation.py
banglanlptoolkit/bnnlpnormalizer.py
banglanlptoolkit/bnnlpnormalizerplus.py
banglanlptoolkit/bntokenizers.py
banglanlptoolkit/seq2seqaug.py
banglanlptoolkit/sequenceclassificationaug.py
banglanlptoolkit/utils.py
banglanlptoolkit-1.1.8.dist-info/LICENSE.txt
banglanlptoolkit-1.1.8.dist-info/METADATA
banglanlptoolkit-1.1.8.dist-info/WHEEL
banglanlptoolkit-1.1.8.dist-info/top_level.txt
banglanlptoolkit-1.1.8.dist-info/RECORD
