Metadata-Version: 2.1
Name: banglanlptoolkit
Version: 1.1.8
Summary: Toolkits for text processing and augmentation for Bangla NLP
Home-page: https://github.com/Kabir5296/banglanlptoolkit
Author: A F M Mahfuzul Kabir
Author-email: <afmmahfuzulkabir@gmail.com>
Keywords: Bangla,NLP,toolkit,punctuation,augmentation,normalizer,tokenize
Classifier: Intended Audience :: Education
Classifier: License :: OSI Approved :: MIT License
Classifier: Operating System :: OS Independent
Classifier: Programming Language :: Python :: 3.8
License-File: LICENSE.txt
Requires-Dist: transformers ==4.42.4
Requires-Dist: torch ==2.3.1
Requires-Dist: bnunicodenormalizer ==0.1.7
Requires-Dist: sentencepiece ==0.2.0
Requires-Dist: langdetect ==1.0.9
Requires-Dist: pandarallel
Requires-Dist: pqdm
